glasto/__init__.py
glasto/client.py
glasto/twenty19.py
glasto/twenty20.py
glasto/util.py
glasto-0.0.4.data/scripts/glasto2019.py
glasto-0.0.4.dist-info/LICENSE
glasto-0.0.4.dist-info/METADATA
glasto-0.0.4.dist-info/WHEEL
glasto-0.0.4.dist-info/top_level.txt
glasto-0.0.4.dist-info/RECORD
